nopassword/__init__.py
nopassword/admin.py
nopassword/forms.py
nopassword/models.py
nopassword/urls.py
nopassword/views.py
nopassword/backends/__init__.py
nopassword/backends/base.py
nopassword/backends/email.py
nopassword/backends/sms.py
nopassword/migrations/0001_initial.py
nopassword/migrations/0002_auto_20190406_1322.py
nopassword/migrations/__init__.py
nopassword/rest/__init__.py
nopassword/rest/serializers.py
nopassword/rest/urls.py
nopassword/rest/views.py
nopassword/templates/registration/logged_out.html
nopassword/templates/registration/login_code.html
nopassword/templates/registration/login_email.txt
nopassword/templates/registration/login_form.html
nopassword/templates/registration/login_sms.txt
nopassword/templates/registration/login_subject.txt
django_nopassword-5.0.0.dist-info/LICENSE
django_nopassword-5.0.0.dist-info/METADATA
django_nopassword-5.0.0.dist-info/WHEEL
django_nopassword-5.0.0.dist-info/top_level.txt
django_nopassword-5.0.0.dist-info/RECORD
